[
  {
      "id": 1,
      "title": "Camp Humphreys",
      "description": "Base militar en Corea del Sur, la más grande de Estados Unidos fuera de territorio estadounidense.",
      "lat": 36.9695,
      "lng": 127.0386,
      "image": "https://example.com/camp-humphreys.jpg",
      "created_date": "1950-07-01"
  },
  {
      "id": 2,
      "title": "Ramstein Air Base",
      "description": "Importante base aérea en Alemania que sirve como centro de operaciones de la USAFE.",
      "lat": 49.4369,
      "lng": 7.6009,
      "image": "https://example.com/ramstein-air-base.jpg",
      "created_date": "1952-08-05"
  },
  {
      "id": 3,
      "title": "Naval Support Activity Bahrain",
      "description": "Base de apoyo naval en el Golfo Pérsico, utilizada para operaciones en Medio Oriente.",
      "lat": 26.2154,
      "lng": 50.6092,
      "image": "https://example.com/nsa-bahrain.jpg",
      "created_date": "1971-10-01"
  },
  {
      "id": 4,
      "title": "Guantánamo Bay Naval Base",
      "description": "Base naval en Cuba conocida por sus instalaciones de detención.",
      "lat": 19.9028,
      "lng": -75.1423,
      "image": "https://example.com/guantanamo-bay.jpg",
      "created_date": "1903-02-23"
  },
  {
      "id": 5,
      "title": "Yokota Air Base",
      "description": "Base aérea de EE.UU. en Japón que sirve como sede de la Fuerza Aérea en el Pacífico.",
      "lat": 35.7485,
      "lng": 139.3483,
      "image": "https://example.com/yokota-air-base.jpg",
      "created_date": "1940-11-01"
  },
  {
      "id": 6,
      "title": "Naval Station Rota",
      "description": "Base naval en España que proporciona apoyo logístico a operaciones en Europa y África.",
      "lat": 36.6224,
      "lng": -6.3574,
      "image": "https://example.com/naval-station-rota.jpg",
      "created_date": "1953-06-01"
  },
  {
      "id": 7,
      "title": "Thule Air Base",
      "description": "Base de la Fuerza Aérea en Groenlandia utilizada para misiones de vigilancia y detección de misiles.",
      "lat": 76.5312,
      "lng": -68.7031,
      "image": "https://example.com/thule-air-base.jpg",
      "created_date": "1951-06-01"
  },
  {
      "id": 8,
      "title": "Diego Garcia Naval Support Facility",
      "description": "Base militar en el Océano Índico utilizada para misiones estratégicas y de vigilancia.",
      "lat": -7.3134,
      "lng": 72.4229,
      "image": "https://example.com/diego-garcia.jpg",
      "created_date": "1971-03-23"
  }
]
